main.py
cli_todo-0.1.0.dist-info/METADATA
cli_todo-0.1.0.dist-info/WHEEL
cli_todo-0.1.0.dist-info/top_level.txt
cli_todo-0.1.0.dist-info/RECORD
