Metadata-Version: 2.2
Name: cli-todo
Version: 0.1.0
Summary: A simple command-line interface (CLI) application to manage your todo list.
Maintainer-email: Syeda Hoorain Ali <jagjets133@gmail.com>
Requires-Python: >=3.12
Requires-Dist: click>=8.1.8
Requires-Dist: inquirer>=3.4.0
